{"schema":"allo-reading-book@1","slug":"224954-bayti-kuluh-ajras","title":"بَيْتِي كُلُّهُ أَجْرَاسٌ","description":"كَيْفَ يُمْكِنُ لِلطِّفْلِ الصَّغِيرِ أَنْ يَنَامَ وَالْأَصْوَاتُ كَثِيرَةٌ مِنْ حَوْلِهِ؟ اكْتَشِفْ مَا يُزْعِجُ صَغِيرَنَا.","language":"Arabic","langCode":"ar","isRtl":true,"level":"1","orientation":"landscape","authors":["Nihal Bishr"],"illustrators":["Zainab Tambawalla"],"originalAuthors":[],"publisher":"Education Above All (EAA)","license":"CC BY 4.0","licenseUrl":"https://creativecommons.org/licenses/by/4.0/","sourceId":"storyweaver","contentType":"story","source":{"id":"storyweaver","name":"StoryWeaver, Pratham Books","url":"https://storyweaver.org.in/en/stories/224954-bayti-kuluh-ajras"},"cover":{"card":"https://static.storyweaver.org.in/illustration_crops/123536/size3/4715c5ce5d3320cc4921d64fde8272ef.jpg","large":"https://static.storyweaver.org.in/illustration_crops/123536/size6/4715c5ce5d3320cc4921d64fde8272ef.jpg"},"audio":{"src":"https://storage.googleapis.com/story-weaver-e2e-production/stories/224954/audios/story/224954-bayti-kuluh-ajras.mp3","cues":[[1,0,0.87],[2,0.87,1.8],[3,1.8,3.92],[4,3.92,5.82],[5,5.82,6.9],[6,6.9,8.12],[7,8.12,8.86],[8,8.86,11.6],[9,11.6,13.68],[10,13.68,14.34],[11,14.34,14.7],[12,14.7,15.22],[13,15.22,15.64],[14,15.64,16.3],[15,16.3,17.12],[16,17.12,19.3],[17,19.3,22.08],[18,22.08,23.54],[19,23.54,24.14],[20,24.14,26.5],[21,26.5,28.1],[22,28.1,28.85],[23,28.85,31.33],[24,31.33,32.39],[25,32.39,32.94],[26,32.94,33.84],[27,33.84,34.88],[28,34.88,38.14],[29,38.14,39.66],[30,39.66,41.4],[31,41.4,42],[32,42,42.5],[33,42.5,44.23],[34,44.23,45.76],[35,45.76,46.48],[36,46.48,46.9],[37,46.9,49.5],[38,49.5,50.62],[39,50.62,51.12],[40,51.12,51.86],[41,51.86,52.56],[42,52.56,54],[43,54,54],[44,54,54.7],[45,54.7,55.04],[46,55.04,55.46],[47,55.46,57.16],[48,57.16,58.52],[49,58.52,59.14],[50,59.14,60.2],[51,60.2,60.8],[52,60.8,61.24],[53,61.24,61.9],[54,61.9,62.4],[55,62.4,62.8],[56,62.8,63.04],[57,63.04,63.8],[58,63.8,66.38],[59,66.38,67.48],[60,67.48,68.6],[61,68.6,70],[62,70,71.12],[63,71.12,71.8],[64,71.8,72.44],[65,72.44,132.44]]},"pages":[{"n":1,"img":"https://storage.googleapis.com/static.storyweaver.org.in/illustration_crops/42427/size6/e27103c93bdc76f7ac347985e2745c04.jpg","text":"كُلَّمَا حَاوَلْتُ النَّوْمَ،","words":[[1,"كُلَّمَا"],[2,"حَاوَلْتُ"],[3,"النَّوْمَ،"]]},{"n":2,"img":"https://storage.googleapis.com/static.storyweaver.org.in/illustration_crops/42428/size6/941ec9e708b3dd613ff835590ca36952.jpg","text":"تِينْجْ \nتُونْجْ \nيُدَقُّ جَرَسُ الْبَابِ.","words":[[4,"تِينْجْ"],[5,"تُونْجْ"],[6,"يُدَقُّ"],[7,"جَرَسُ"],[8,"الْبَابِ."]]},{"n":3,"img":"https://storage.googleapis.com/static.storyweaver.org.in/illustration_crops/42429/size6/daf5d80257d7757f273b0e638c1aa83e.jpg","text":"الْآنَ أُحَاوِلُ أَنْ أَنَامَ عَلَى الْجَانِبِ الْآخَرِ، ثُمَّ...","words":[[9,"الْآنَ"],[10,"أُحَاوِلُ"],[11,"أَنْ"],[12,"أَنَامَ"],[13,"عَلَى"],[14,"الْجَانِبِ"],[15,"الْآخَرِ،"],[16,"ثُمَّ..."]]},{"n":4,"img":"https://storage.googleapis.com/static.storyweaver.org.in/illustration_crops/42430/size6/8eff213881bc43a97000735ac1437487.jpg","text":"بُزْزْزْ، بُزْزْزْ \nيَرِنُّ الْجَوَّالُ.","words":[[17,"بُزْزْزْ،"],[18,"بُزْزْزْ"],[19,"يَرِنُّ"],[20,"الْجَوَّالُ."]]},{"n":5,"img":"https://storage.googleapis.com/static.storyweaver.org.in/illustration_crops/42431/size6/faab3c34896ab125efc89a508d823e9d.jpg","text":"وَأُحَاوِلُ مَرَّةً أُخْرَى،","words":[[21,"وَأُحَاوِلُ"],[22,"مَرَّةً"],[23,"أُخْرَى،"]]},{"n":6,"img":"https://storage.googleapis.com/static.storyweaver.org.in/illustration_crops/42432/size6/1b0a19a8fb907709978d709716d171d5.jpg","text":"وَفِي هَذِهِ الْمَرَّةِ \nإِنَّهُ...\nدُونْجْ!","words":[[24,"وَفِي"],[25,"هَذِهِ"],[26,"الْمَرَّةِ"],[27,"إِنَّهُ..."],[28,"دُونْجْ!"]]},{"n":7,"img":"https://storage.googleapis.com/static.storyweaver.org.in/illustration_crops/42433/size6/504ad6db7af03ea0cf3f068aaa97f631.jpg","text":"تِرِرِرِنْجْ تِرِرِرِنْجْ!\nمَاذَا كَانَ هَذَا؟!","words":[[29,"تِرِرِرِنْجْ"],[30,"تِرِرِرِنْجْ!"],[31,"مَاذَا"],[32,"كَانَ"],[33,"هَذَا؟!"]]},{"n":8,"img":"https://storage.googleapis.com/static.storyweaver.org.in/illustration_crops/42434/size6/e92acdf20a2bfa42ca815a8d1ea6836b.jpg","text":"دَرَّاجَةٌ مُسْرِعَةٌ فِي\n الطَّرِيقِ!","words":[[34,"دَرَّاجَةٌ"],[35,"مُسْرِعَةٌ"],[36,"فِي"],[37,"الطَّرِيقِ!"]]},{"n":9,"img":"https://storage.googleapis.com/static.storyweaver.org.in/illustration_crops/42435/size6/0c7486c1f4053dec7569499807adc973.jpg","text":"تَقُولُ أُمِّي عِنْدَمَا تَرَانِي مُسْتَيْقِظًا: \n\"مَاذَا؟! أَلَمْ تَنَمْ بَعْدُ\"؟!","words":[[38,"تَقُولُ"],[39,"أُمِّي"],[40,"عِنْدَمَا"],[41,"تَرَانِي"],[42,"مُسْتَيْقِظًا:"],[43,"\""],[44,"مَاذَا؟!"],[45,"أَلَمْ"],[46,"تَنَمْ"],[47,"بَعْدُ\"؟!"]]},{"n":10,"img":"https://storage.googleapis.com/static.storyweaver.org.in/illustration_crops/42436/size6/298903ef37ef23c2dd40bbc3e9982794.jpg","text":"فَأَقُولُ لَهَا بِعَيْنَيَّ: \n\"وَلَكِنْ يَا أُمِّي كَيْفَ لِي أَنْ أَنَامَ\"؟!","words":[[48,"فَأَقُولُ"],[49,"لَهَا"],[50,"بِعَيْنَيَّ:"],[51,"\"وَلَكِنْ"],[52,"يَا"],[53,"أُمِّي"],[54,"كَيْفَ"],[55,"لِي"],[56,"أَنْ"],[57,"أَنَامَ\"؟!"]]},{"n":11,"img":"https://storage.googleapis.com/static.storyweaver.org.in/illustration_crops/42437/size6/78f6134743656be792dc6af641f6909c.jpg","text":"\"تِينْجْ، بُزْزْزْ،\n دُونْجْ، تِرِنْجْ!\nالْبَيْتُ كُلُّهُ مَلِيءٌ\n بِالْأَجْرَاسِ\"!","words":[[58,"\"تِينْجْ،"],[59,"بُزْزْزْ،"],[60,"دُونْجْ،"],[61,"تِرِنْجْ!"],[62,"الْبَيْتُ"],[63,"كُلُّهُ"],[64,"مَلِيءٌ"],[65,"بِالْأَجْرَاسِ\"!"]]}],"stats":{"pages":11,"words":64}}