{
  "schema": "allo-reading-book@1",
  "slug": "bloom-134fff31-untitled-th",
  "title": "นางฟ้าในร่างนางมาร",
  "description": "เด็กๆกลับมาตั้งใจเรียนเพราะเห็นความจริงใจของคุณครูที่มีต่อลูกศิษย์",
  "language": "Thai",
  "langCode": "th",
  "isRtl": false,
  "level": "4",
  "orientation": "portrait",
  "sourceId": "bloom",
  "contentType": "story",
  "subjects": [],
  "authors": [
    "มูลนิธิศุภนิมิตแห่งประเทศไทย"
  ],
  "illustrators": [],
  "originalAuthors": [],
  "publisher": "มูลนิธิศุภนิมิตแห่งประเทศไทย",
  "license": "CC BY",
  "licenseUrl": "https://creativecommons.org/licenses/by/4.0/",
  "source": {
    "id": "bloom",
    "name": "Bloom Library",
    "url": "https://bloomlibrary.org/book/PFgGjZkjGs"
  },
  "cover": "https://s3.amazonaws.com/BloomLibraryBooks/muicrab.14%40gmail.com%2f134fff31-adfd-41d1-812a-efec8e528a40%2f%e0%b8%99%e0%b8%b2%e0%b8%87%e0%b8%9f%e0%b9%89%e0%b8%b2%e0%b9%83%e0%b8%99%e0%b8%a3%e0%b9%88%e0%b8%b2%e0%b8%87%e0%b8%99%e0%b8%b2%e0%b8%87%e0%b8%a1%e0%b8%b2%e0%b8%a3%2fหน้าปก121.jpg",
  "audio": null,
  "pages": [
    {
      "n": 1,
      "img": "https://s3.amazonaws.com/BloomLibraryBooks/muicrab.14%40gmail.com%2f134fff31-adfd-41d1-812a-efec8e528a40%2f%e0%b8%99%e0%b8%b2%e0%b8%87%e0%b8%9f%e0%b9%89%e0%b8%b2%e0%b9%83%e0%b8%99%e0%b8%a3%e0%b9%88%e0%b8%b2%e0%b8%87%e0%b8%99%e0%b8%b2%e0%b8%87%e0%b8%a1%e0%b8%b2%e0%b8%a3%2f92101.jpg",
      "text": "สวัสดีค่ะ เด็ก ๆ ที่น่ารักของคุณครู ครูยินดีมากที่ได้มีโอกาสจัดทําหนังสือ นิทานให้กับเด็ก ๆ ได้อ่าน หนังสือนิทานเรื่องนี้ได้รับความร่วมมือ จากเพื่อน ๆโรงเรียน ตชด.บ้านแม่กลองคี หมูที่ ๓ ตําบลโมโกร อําเภออุ้มผาง จังหวัดตาก เรียบเรียงโดยครูและนักเรียนโรงเรียน ตชด.บ้านแม่กลองคีหนังสือนิทานเล่มนี้จัดทําขึ้นมาเพื่อให้เด็ก ๆ ได้ฝึกการอ่านออกเสียง ซึ่งเด็ก ๆ จะได้ ข้อคิดและคติสอนใจจากนิทานเรื่องนี้คุณครูหวังเป็นอยางยิ่งว่าหนังสือนิทานเรื่องนี้จะเป็นประโยชน์ต่อเด็ก ๆ ซึ่งจะได้ข้อคิด คติสอนใจ และความรู้ที่ได้รับไปปรับใช้ในชีวิตประจําวัน เพื่อการอยู่ร่วมกันอย่างสงบสุขของสังคมต่อไป"
    },
    {
      "n": 2,
      "img": "https://s3.amazonaws.com/BloomLibraryBooks/muicrab.14%40gmail.com%2f134fff31-adfd-41d1-812a-efec8e528a40%2f%e0%b8%99%e0%b8%b2%e0%b8%87%e0%b8%9f%e0%b9%89%e0%b8%b2%e0%b9%83%e0%b8%99%e0%b8%a3%e0%b9%88%e0%b8%b2%e0%b8%87%e0%b8%99%e0%b8%b2%e0%b8%87%e0%b8%a1%e0%b8%b2%e0%b8%a3%2f%e0%b8%ab%e0%b9%911.jpg",
      "text": "ณ โรงเรียนแห่งหนึ่ง มีนักเรียนกลุ่มหนึ่ง ไม่ค่อยชอบเรียนหนังสือและโดดเรียนบ่อยๆ แต่มาโรงเรียนทุกวัน ซึ่งทั้งคุณครูและนักเรียนในโรงเรียนตั้งฉายาให้ว่าแก๊งตัวป่วน"
    },
    {
      "n": 3,
      "img": "https://s3.amazonaws.com/BloomLibraryBooks/muicrab.14%40gmail.com%2f134fff31-adfd-41d1-812a-efec8e528a40%2f%e0%b8%99%e0%b8%b2%e0%b8%87%e0%b8%9f%e0%b9%89%e0%b8%b2%e0%b9%83%e0%b8%99%e0%b8%a3%e0%b9%88%e0%b8%b2%e0%b8%87%e0%b8%99%e0%b8%b2%e0%b8%87%e0%b8%a1%e0%b8%b2%e0%b8%a3%2f%e0%b8%ab%e0%b9%921.jpg",
      "text": "และมีคุณครูคนหนึ่งซึ่งในสายตานักเรียน ครูคนนี้คือ นางมารร้ายดีๆนั่นเอง"
    },
    {
      "n": 4,
      "img": "https://s3.amazonaws.com/BloomLibraryBooks/muicrab.14%40gmail.com%2f134fff31-adfd-41d1-812a-efec8e528a40%2f%e0%b8%99%e0%b8%b2%e0%b8%87%e0%b8%9f%e0%b9%89%e0%b8%b2%e0%b9%83%e0%b8%99%e0%b8%a3%e0%b9%88%e0%b8%b2%e0%b8%87%e0%b8%99%e0%b8%b2%e0%b8%87%e0%b8%a1%e0%b8%b2%e0%b8%a3%2f%e0%b8%ab%e0%b9%931.jpg",
      "text": "ครูปองใจพูดขึ้นว่า “จะไปไหน”ครูปองใจขึ้นเสียงถามนักเรียนแก๊งตัวป่วน ไปเข้าห้องน้ำครับ รีบไปแล้วรีบกลับมานะ"
    },
    {
      "n": 5,
      "img": "https://s3.amazonaws.com/BloomLibraryBooks/muicrab.14%40gmail.com%2f134fff31-adfd-41d1-812a-efec8e528a40%2f%e0%b8%99%e0%b8%b2%e0%b8%87%e0%b8%9f%e0%b9%89%e0%b8%b2%e0%b9%83%e0%b8%99%e0%b8%a3%e0%b9%88%e0%b8%b2%e0%b8%87%e0%b8%99%e0%b8%b2%e0%b8%87%e0%b8%a1%e0%b8%b2%e0%b8%a3%2f%e0%b8%ab%e0%b9%941.jpg",
      "text": "หลังครูปองใจพูดจากวันนั้นแก๊งตัวป่วน เริ่มไม่ค่อยชอบครูปองใจละ เลยคิดหาวิธีแกล้งสารพัด จนทำให้คุณครูท้อร้องให้เสียใจหลายๆครั้ง"
    },
    {
      "n": 6,
      "img": "https://s3.amazonaws.com/BloomLibraryBooks/muicrab.14%40gmail.com%2f134fff31-adfd-41d1-812a-efec8e528a40%2f%e0%b8%99%e0%b8%b2%e0%b8%87%e0%b8%9f%e0%b9%89%e0%b8%b2%e0%b9%83%e0%b8%99%e0%b8%a3%e0%b9%88%e0%b8%b2%e0%b8%87%e0%b8%99%e0%b8%b2%e0%b8%87%e0%b8%a1%e0%b8%b2%e0%b8%a3%2f%e0%b8%ab%e0%b9%951.jpg",
      "text": "แก๊งตัวป่วนเริ่มออกฤทธิ์แกล้งคุณครูปองใจด้วยวิธีต่างๆ เช่น เอาตุ๊กแกปลอมไปวางไว้บนโต๊ะและเอางูปลอมไปวางไว้หน้าประตูทางเข้า"
    },
    {
      "n": 7,
      "img": "https://s3.amazonaws.com/BloomLibraryBooks/muicrab.14%40gmail.com%2f134fff31-adfd-41d1-812a-efec8e528a40%2f%e0%b8%99%e0%b8%b2%e0%b8%87%e0%b8%9f%e0%b9%89%e0%b8%b2%e0%b9%83%e0%b8%99%e0%b8%a3%e0%b9%88%e0%b8%b2%e0%b8%87%e0%b8%99%e0%b8%b2%e0%b8%87%e0%b8%a1%e0%b8%b2%e0%b8%a3%2f%e0%b8%ab%e0%b9%961.jpg",
      "text": "ครูปองใจเริ่มอารมณ์เสีย โมโหแก๊งตัวป่วนจนหน้าแดงหน้าดำเชียว"
    },
    {
      "n": 8,
      "img": "https://s3.amazonaws.com/BloomLibraryBooks/muicrab.14%40gmail.com%2f134fff31-adfd-41d1-812a-efec8e528a40%2f%e0%b8%99%e0%b8%b2%e0%b8%87%e0%b8%9f%e0%b9%89%e0%b8%b2%e0%b9%83%e0%b8%99%e0%b8%a3%e0%b9%88%e0%b8%b2%e0%b8%87%e0%b8%99%e0%b8%b2%e0%b8%87%e0%b8%a1%e0%b8%b2%e0%b8%a3%2f%e0%b8%ab%e0%b9%971.jpg",
      "text": "ครูปองใจลงโทษแก๊งตัวป่วน ด้วยการออกกำลังกายเบาๆ ลุก-นั่ง 100 ครั้ง"
    },
    {
      "n": 9,
      "img": "https://s3.amazonaws.com/BloomLibraryBooks/muicrab.14%40gmail.com%2f134fff31-adfd-41d1-812a-efec8e528a40%2f%e0%b8%99%e0%b8%b2%e0%b8%87%e0%b8%9f%e0%b9%89%e0%b8%b2%e0%b9%83%e0%b8%99%e0%b8%a3%e0%b9%88%e0%b8%b2%e0%b8%87%e0%b8%99%e0%b8%b2%e0%b8%87%e0%b8%a1%e0%b8%b2%e0%b8%a3%2f%e0%b8%ab%e0%b9%981.jpg",
      "text": "ครูปองใจกลุ้มใจกับแก๊งตัวป่วนมากๆ แต่คิดหาวิธีจะปรับนิสัยแก๊งตัวป่วนให้ดีขึ้น"
    },
    {
      "n": 10,
      "img": "https://s3.amazonaws.com/BloomLibraryBooks/muicrab.14%40gmail.com%2f134fff31-adfd-41d1-812a-efec8e528a40%2f%e0%b8%99%e0%b8%b2%e0%b8%87%e0%b8%9f%e0%b9%89%e0%b8%b2%e0%b9%83%e0%b8%99%e0%b8%a3%e0%b9%88%e0%b8%b2%e0%b8%87%e0%b8%99%e0%b8%b2%e0%b8%87%e0%b8%a1%e0%b8%b2%e0%b8%a3%2f%e0%b8%ab%e0%b9%991.jpg",
      "text": "วันต่อมาครูปองใจคิดหาวิธีพยายามจะให้แก๊งตัวป่วนหันมาสนใจเรียนมากขึ้น แต่ก็ยังไม่สำเร็จ"
    },
    {
      "n": 11,
      "img": "https://s3.amazonaws.com/BloomLibraryBooks/muicrab.14%40gmail.com%2f134fff31-adfd-41d1-812a-efec8e528a40%2f%e0%b8%99%e0%b8%b2%e0%b8%87%e0%b8%9f%e0%b9%89%e0%b8%b2%e0%b9%83%e0%b8%99%e0%b8%a3%e0%b9%88%e0%b8%b2%e0%b8%87%e0%b8%99%e0%b8%b2%e0%b8%87%e0%b8%a1%e0%b8%b2%e0%b8%a3%2f%e0%b8%ab%e0%b9%91%e0%b9%901.jpg",
      "text": "ครูปองใจสังเกตพฤติกรรมของแก๊งตัวป่วนและหากิจกรรมเสริมเพื่อให้แก๊งตัวป่วนทำ คือเก็บขยะรีไซเคิลมาส่งทุกๆเช้าพอครบหนึ่งเดือนครูปองใจจะนำขยะรีไซเคิลไปขายพอได้เงินมาแล้วมามอบให้กับแก๊งตัวป่วนเป็นรายได้ระหว่างเรียนทำให้แก๊งตัวป่วนหันมาสนใจเรียนมากขึ้น"
    },
    {
      "n": 12,
      "img": "https://s3.amazonaws.com/BloomLibraryBooks/muicrab.14%40gmail.com%2f134fff31-adfd-41d1-812a-efec8e528a40%2f%e0%b8%99%e0%b8%b2%e0%b8%87%e0%b8%9f%e0%b9%89%e0%b8%b2%e0%b9%83%e0%b8%99%e0%b8%a3%e0%b9%88%e0%b8%b2%e0%b8%87%e0%b8%99%e0%b8%b2%e0%b8%87%e0%b8%a1%e0%b8%b2%e0%b8%a3%2f%e0%b8%ab%e0%b9%91%e0%b9%911.jpg",
      "text": "อยู่มาวันหนึ่งแก๊งตัวป่วนไปมีเรื่องกับนักเลงในหมู่บ้าน มีคนพบเห็นและได้ไปแจ้งครูปองใจให้ทราบ"
    },
    {
      "n": 13,
      "img": "https://s3.amazonaws.com/BloomLibraryBooks/muicrab.14%40gmail.com%2f134fff31-adfd-41d1-812a-efec8e528a40%2f%e0%b8%99%e0%b8%b2%e0%b8%87%e0%b8%9f%e0%b9%89%e0%b8%b2%e0%b9%83%e0%b8%99%e0%b8%a3%e0%b9%88%e0%b8%b2%e0%b8%87%e0%b8%99%e0%b8%b2%e0%b8%87%e0%b8%a1%e0%b8%b2%e0%b8%a3%2f%e0%b8%ab%e0%b9%91%e0%b9%921.jpg",
      "text": "ครูปองใจวิ่งมาห้ามและช่วยเหลือแก๊งตัวป่วนจนทำให้โดนลูกหลง ถูกทำร้ายได้รับบาดเจ็บ"
    },
    {
      "n": 14,
      "img": "https://s3.amazonaws.com/BloomLibraryBooks/muicrab.14%40gmail.com%2f134fff31-adfd-41d1-812a-efec8e528a40%2f%e0%b8%99%e0%b8%b2%e0%b8%87%e0%b8%9f%e0%b9%89%e0%b8%b2%e0%b9%83%e0%b8%99%e0%b8%a3%e0%b9%88%e0%b8%b2%e0%b8%87%e0%b8%99%e0%b8%b2%e0%b8%87%e0%b8%a1%e0%b8%b2%e0%b8%a3%2f%e0%b8%ab%e0%b9%91%e0%b9%931.jpg",
      "text": "และแล้วแก๊งตัวป่วนก็แลเห็นความดีของคุณครูปองใจ สำนึกผิดและกลับมาตั้งใจเรียนและคิดได้ว่าคุณครูปองใจคือ “นางฟ้าในร่างนางมารนั่นเอง”"
    },
    {
      "n": 15,
      "img": null,
      "text": "แก่นเรื่อง:การมองคนตัดสินคน\nชื่อเรื่อง :นางฟ้าในร่างนางมาร\nข้อคิด :อย่ามองคนแต่ภายนอก\nเรื่องย่อ :นักเรียนกลุ่มหนึ่งดื้อและเกเรไม่ตั้งใจเรียนซึ่งมีชื่อกลุ่มว่าแก๊งตัวป่วน ชอบแกล้งครูแล้ววันหนึ่งนักเรียนมีเรื่องทะเลาะวิวาทกับนักเลงในหมู่บ้านครูปองใจมาห้ามแล้วโดนลูกหลงถูกทำร้ายไปด้วยจากนั้นแก๊งตัวป่วนเห็นความใจดีของครูปองใจจึงกลับตัวเป็นคนดีและตั้งใจเรียน"
    },
    {
      "n": 16,
      "img": null,
      "text": "เค้าโครงเรื่อง:\nด.ญ.ชลิตา ตรรกชัยภิบาล นักเรียน รร. ตชด.บ้านแม่กลองคี ด.ญ.ชะคึพอ - นักเรียน รร. ตชด.บ้านแม่กลองคี ด.ญ.สรินดา ฉัตรรัตนาเหม นักเรียน รร. ตชด.บ้านแม่กลองคี ด.ญ.ศุภรัตน์ วนาศรีธาดา นักเรียน รร. ตชด.บ้านแม่กลองคี\nนางนิตยา นภาสว่างไพร ครู รร. ตชด.บ้านแม่กลองคี\nน.ส.สุนีย์ ชนชีวารัตน์ ครู รร. ตชด.บ้านแม่กลองคี\nคณะผู้จัดทำ:\nด.ญ.ชลิตา ตรรกชัยภิบาล นักเรียน ร.ร. ตชด.บ้านแม่กลองคี ด.ญ.ชะคึพอ - นักเรียน ร.ร. ตชด.บ้านแม่กลองคี ด.ญ.สรินดา ฉัตรรัตนาเหม นักเรียน ร.ร. ตชด.บ้านแม่กลองคี ด.ญ.ศุภรัตน์ วนาศรีธาดา นักเรียน ร.ร. ตชด.บ้านแม่กลองคี\nนางนิตยา นภาสว่างไพร ครู ร.ร. ตชด.บ้านแม่กลองคี\nน.ส.สุนีย์ ชนชีวารัตน์ ครู ร.ร. ตชด.บ้านแม่กลองคี"
    }
  ],
  "stats": {
    "pages": 16,
    "words": 140
  }
}
